[
    {
        "id": 1388534400000,
        "author": "Pete Hunt",
        "text": "Hey there!"
    },
    {
        "id": 1420070400000,
        "author": "Paul O’Shannessy",
        "text": "React is *great*!"
    },
    {
        "id": 1479492627318,
        "author": "Lizard Man",
        "text": "<3 Wrath of the lizard!"
    },
    {
        "id": 1540498888548,
        "author": "Other guy",
        "text": "Ill just be over here.."
    },
    {
        "id": 1540498913644,
        "author": "Me",
        "text": "I rule?"
    },
    {
        "id": 1541274886825,
        "author": "Hello Darkness",
        "text": "My old friend, Ive come to talk with you again"
    }
]